Metadata-Version: 1.1
Name: psh
Version: 0.2.5
Summary: Process management library
Home-page: http://konishchevdmitry.github.com/psh/
Author: Dmitry Konishchev
Author-email: konishchev@gmail.com
License: GPL3
Platform: unix
Platform: linux
Platform: osx
Classifier: Development Status :: 4 - Beta
Classifier: Intended Audience :: Developers
Classifier: License :: OSI Approved :: GNU General Public License v3 (GPLv3)
Classifier: Operating System :: MacOS :: MacOS X
Classifier: Operating System :: POSIX
Classifier: Operating System :: Unix
Classifier: Programming Language :: Python :: 2
Classifier: Programming Language :: Python :: 3
Classifier: Topic :: Software Development :: Libraries :: Python Modules
